MANIFEST.in
setup.py
memcached_memoize/__init__.py
memcached_memoize/cached_data.py
memcached_memoize/functiontools.py
memcached_memoize/utils.py
memcached_memoize.egg-info/PKG-INFO
memcached_memoize.egg-info/SOURCES.txt
memcached_memoize.egg-info/dependency_links.txt
memcached_memoize.egg-info/not-zip-safe
memcached_memoize.egg-info/requires.txt
memcached_memoize.egg-info/top_level.txt
memcached_memoize/decorators/__init__.py
memcached_memoize/decorators/base.py
memcached_memoize/decorators/circuit_breaker.py
requirements/dependencies.txt